dripostal/__init__.py
dripostal/aio.py
dripostal/schemas.py
dripostal-0.1.1.dist-info/LICENSE
dripostal-0.1.1.dist-info/WHEEL
dripostal-0.1.1.dist-info/METADATA
dripostal-0.1.1.dist-info/RECORD
