Metadata-Version: 2.1
Name: dripostal
Version: 0.1.1
Summary: A tiny API client for the Pelias Libpostal REST service.
Home-page: https://dribia.github.io/dripostal
License: MIT
Author: Dribia Data Research
Author-email: opensource@dribia.com
Maintainer: Nabil Kakeh
Maintainer-email: nabil@dribia.com
Requires-Python: >=3.6.2,<4.0
Classifier: License :: OSI Approved :: MIT License
Classifier: Programming Language :: Python :: 3
Classifier: Programming Language :: Python :: 3.7
Classifier: Programming Language :: Python :: 3.8
Classifier: Programming Language :: Python :: 3.9
Provides-Extra: aiohttp
Requires-Dist: aiohttp (>=3.7.4,<4.0.0); extra == "aiohttp"
Requires-Dist: importlib-metadata (>=1.0,<5.0); python_version < "3.8"
Requires-Dist: pydantic (>=1.8.2,<2.0.0)
Project-URL: Documentation, https://dribia.github.io/dripostal
Project-URL: Repository, https://github.com/dribia/dripostal
